[
  {
    "title": "The Whispering Woods",
    "author": "Elena Marlowe",
    "genre": "Fantasy",
    "rating": 4.8,
    "summary": "A young girl discovers an ancient forest spirit that guards the balance between light and dark.",
    "coverImage": "https://i.ibb.co.com/vxMCMwXP/81o-SPz-P9-TRL-SY466.jpg",
    "userEmail": "elena.marlowe@example.com"
  },
  {
    "title": "Crimson Echoes",
    "author": "James Rowland",
    "genre": "Mystery",
    "rating": 4.5,
    "summary": "A detective must unravel a series of murders linked by a haunting melody.",
    "coverImage": "https://i.ibb.co.com/vxMCMwXP/81o-SPz-P9-TRL-SY466.jpg",
    "userEmail": "james.rowland@example.com"
  },
  {
    "title": "The Quantum Paradox",
    "author": "Dr. Amelia Frost",
    "genre": "Science Fiction",
    "rating": 4.7,
    "summary": "A physicist accidentally opens a gateway to alternate realities.",
    "coverImage": "https://i.ibb.co.com/vxMCMwXP/81o-SPz-P9-TRL-SY466.jpg",
    "userEmail": "amelia.frost@example.com"
  },
  {
    "title": "Shadows of Verona",
    "author": "Isabella Conti",
    "genre": "Historical Romance",
    "rating": 4.2,
    "summary": "In Renaissance Italy, forbidden love blooms amidst political intrigue.",
    "coverImage": "https://i.ibb.co.com/vxMCMwXP/81o-SPz-P9-TRL-SY466.jpg",
    "userEmail": "isabella.conti@example.com"
  },
  {
    "title": "Beneath the Crimson Sea",
    "author": "Liam Carter",
    "genre": "Adventure",
    "rating": 4.6,
    "summary": "A diver searches for a lost civilization beneath the Indian Ocean.",
    "coverImage": "https://i.ibb.co.com/vxMCMwXP/81o-SPz-P9-TRL-SY466.jpg",
    "userEmail": "liam.carter@example.com"
  },
  {
    "title": "Fragments of Tomorrow",
    "author": "Noah Sterling",
    "genre": "Dystopian",
    "rating": 4.3,
    "summary": "In a world run by AI, a rebel programmer fights for human freedom.",
    "coverImage": "https://i.ibb.co.com/vxMCMwXP/81o-SPz-P9-TRL-SY466.jpg",
    "userEmail": "noah.sterling@example.com"
  },
  {
    "title": "The Celestial Library",
    "author": "Sofia Liang",
    "genre": "Fantasy",
    "rating": 5.0,
    "summary": "A librarian discovers books that can alter reality itself.",
    "coverImage": "https://i.ibb.co.com/vxMCMwXP/81o-SPz-P9-TRL-SY466.jpg",
    "userEmail": "sofia.liang@example.com"
  },
  {
    "title": "Ashes and Embers",
    "author": "David Monroe",
    "genre": "Drama",
    "rating": 4.1,
    "summary": "A firefighter struggles to rebuild his life after a devastating loss.",
    "coverImage": "https://i.ibb.co.com/vxMCMwXP/81o-SPz-P9-TRL-SY466.jpg",
    "userEmail": "david.monroe@example.com"
  },
  {
    "title": "The Infinite Canvas",
    "author": "Clara Nguyen",
    "genre": "Art / Non-Fiction",
    "rating": 4.9,
    "summary": "Exploring creativity through the lens of modern digital artists.",
    "coverImage": "https://i.ibb.co.com/vxMCMwXP/81o-SPz-P9-TRL-SY466.jpg",
    "userEmail": "clara.nguyen@example.com"
  },
  {
    "title": "Echoes in the Fog",
    "author": "Marcus Hale",
    "genre": "Thriller",
    "rating": 4.4,
    "summary": "A small-town journalist uncovers a government cover-up hidden in plain sight.",
    "coverImage": "https://i.ibb.co.com/vxMCMwXP/81o-SPz-P9-TRL-SY466.jpg",
    "userEmail": "marcus.hale@example.com"
  },
  {
    "title": "The Alchemist’s Legacy",
    "author": "Talia Reyes",
    "genre": "Fantasy",
    "rating": 4.6,
    "summary": "An apprentice uncovers her master’s dangerous secret to eternal life.",
    "coverImage": "https://i.ibb.co.com/vxMCMwXP/81o-SPz-P9-TRL-SY466.jpg",
    "userEmail": "talia.reyes@example.com"
  },
  {
    "title": "Silent Fractures",
    "author": "Henry Wallace",
    "genre": "Psychological Fiction",
    "rating": 4.3,
    "summary": "A psychiatrist questions his sanity after treating a patient who knows his past.",
    "coverImage": "https://i.ibb.co.com/vxMCMwXP/81o-SPz-P9-TRL-SY466.jpg",
    "userEmail": "henry.wallace@example.com"
  },
  {
    "title": "Winds of the Desert",
    "author": "Farah Al-Masri",
    "genre": "Historical Fiction",
    "rating": 4.8,
    "summary": "A Bedouin woman leads her tribe through a time of war and change.",
    "coverImage": "https://i.ibb.co.com/vxMCMwXP/81o-SPz-P9-TRL-SY466.jpg",
    "userEmail": "farah.masri@example.com"
  },
  {
    "title": "Neon Skyline",
    "author": "Ethan Brooks",
    "genre": "Cyberpunk",
    "rating": 4.5,
    "summary": "A hacker unearths a corporate conspiracy in a neon-soaked megacity.",
    "coverImage": "https://i.ibb.co.com/vxMCMwXP/81o-SPz-P9-TRL-SY466.jpg",
    "userEmail": "ethan.brooks@example.com"
  },
  {
    "title": "Threads of Fate",
    "author": "Mira Patel",
    "genre": "Mythology / Fantasy",
    "rating": 4.7,
    "summary": "Three sisters control destiny itself — until one decides to change her own fate.",
    "coverImage": "https://i.ibb.co.com/vxMCMwXP/81o-SPz-P9-TRL-SY466.jpg",
    "userEmail": "mira.patel@example.com"
  },
  {
    "title": "The Forgotten Manuscript",
    "author": "Julian Cross",
    "genre": "Mystery",
    "rating": 4.4,
    "summary": "A professor uncovers a hidden message in an ancient text.",
    "coverImage": "https://i.ibb.co.com/vxMCMwXP/81o-SPz-P9-TRL-SY466.jpg",
    "userEmail": "julian.cross@example.com"
  },
  {
    "title": "Breathe Again",
    "author": "Ava Thompson",
    "genre": "Romance / Drama",
    "rating": 4.2,
    "summary": "Two lost souls find healing and love after heartbreak.",
    "coverImage": "https://i.ibb.co.com/vxMCMwXP/81o-SPz-P9-TRL-SY466.jpg",
    "userEmail": "ava.thompson@example.com"
  },
  {
    "title": "The Iron Horizon",
    "author": "Caleb Dray",
    "genre": "Steampunk",
    "rating": 4.6,
    "summary": "An airship engineer battles sky pirates for control of a powerful relic.",
    "coverImage": "https://i.ibb.co.com/vxMCMwXP/81o-SPz-P9-TRL-SY466.jpg",
    "userEmail": "caleb.dray@example.com"
  },
  {
    "title": "Between Two Worlds",
    "author": "Nadia Karim",
    "genre": "Contemporary Fiction",
    "rating": 4.3,
    "summary": "A young immigrant navigates love, identity, and belonging in a new country.",
    "coverImage": "https://i.ibb.co.com/vxMCMwXP/81o-SPz-P9-TRL-SY466.jpg",
    "userEmail": "nadia.karim@example.com"
  },
  {
    "title": "The Starlit Voyage",
    "author": "Leo Anderson",
    "genre": "Science Fiction",
    "rating": 4.9,
    "summary": "A starship crew ventures beyond known space to find a lost colony.",
    "coverImage": "https://i.ibb.co.com/vxMCMwXP/81o-SPz-P9-TRL-SY466.jpg",
    "userEmail": "leo.anderson@example.com"
  },
  {
    "title": "The Garden of Secrets",
    "author": "Hannah Clarke",
    "genre": "Mystery / Romance",
    "rating": 4.4,
    "summary": "A botanist uncovers a love story buried in a centuries-old garden.",
    "coverImage": "https://i.ibb.co.com/vxMCMwXP/81o-SPz-P9-TRL-SY466.jpg",
    "userEmail": "hannah.clarke@example.com"
  },
  {
    "title": "Echoes of the Moon",
    "author": "Ren Takahashi",
    "genre": "Fantasy / Adventure",
    "rating": 4.7,
    "summary": "A moon priest must reclaim the celestial balance before darkness consumes the realm.",
    "coverImage": "https://i.ibb.co.com/vxMCMwXP/81o-SPz-P9-TRL-SY466.jpg",
    "userEmail": "ren.takahashi@example.com"
  },
  {
    "title": "The Silent City",
    "author": "Olivia Grant",
    "genre": "Post-Apocalyptic",
    "rating": 4.5,
    "summary": "After the fall of civilization, one survivor searches for signs of life in a ruined metropolis.",
    "coverImage": "https://i.ibb.co.com/vxMCMwXP/81o-SPz-P9-TRL-SY466.jpg",
    "userEmail": "olivia.grant@example.com"
  },
  {
    "title": "Waves of Memory",
    "author": "Jonas Müller",
    "genre": "Literary Fiction",
    "rating": 4.8,
    "summary": "An aging sailor recalls the loves and losses that defined his life.",
    "coverImage": "https://i.ibb.co.com/vxMCMwXP/81o-SPz-P9-TRL-SY466.jpg",
    "userEmail": "jonas.muller@example.com"
  }
]